mobject_klixz/__init__.py
mobject_klixz/mobject.py
mobject_klixz-0.1.3.dist-info/METADATA
mobject_klixz-0.1.3.dist-info/WHEEL
mobject_klixz-0.1.3.dist-info/top_level.txt
mobject_klixz-0.1.3.dist-info/RECORD
