Metadata-Version: 2.4
Name: mobject-klixz
Version: 0.1.3
Summary: A dynamic python base object.
Author-email: Sebastian Mau <klixz09@gmail.com>
License: MIT
Project-URL: HomePage, https://github.com/aWsKlixz/MObject
Requires-Python: >=3.11
